filter_optimizer/Version.py
filter_optimizer/__init__.py
filter_optimizer/display_result.py
filter_optimizer/filter_optimizer.py
filter_optimizer/filterplot.py
filter_optimizer/parse_result.py
filter_optimizer/showfromlog.py
filter_optimizer-0.2.dist-info/licenses/LICENSE
filter_optimizer-0.2.dist-info/METADATA
filter_optimizer-0.2.dist-info/WHEEL
filter_optimizer-0.2.dist-info/entry_points.txt
filter_optimizer-0.2.dist-info/top_level.txt
filter_optimizer-0.2.dist-info/RECORD
