Metadata-Version: 2.4
Name: filter-optimizer
Version: 0.2
Summary: Optimize digital filters with differential evolution
Home-page: https://github.com/schlatterbeck/filter-optimizer
Author: Ralf Schlatterbeck
Author-email: Ralf Schlatterbeck <rsc@runtux.com>
License-Expression: MIT
Project-URL: Homepage, https://github.com/schlatterbeck/filter-optimizer
Project-URL: Bug Tracker, https://github.com/schlatterbeck/filter-optimizer/issues
Platform: Any
Classifier: Development Status :: 3 - Alpha
Classifier: Operating System :: OS Independent
Classifier: Programming Language :: Python
Classifier: Intended Audience :: Science/Research
Classifier: Intended Audience :: Other Audience
Requires-Python: >=3.7
License-File: LICENSE
Requires-Dist: matplotlib
Requires-Dist: numpy
Requires-Dist: scipy
Requires-Dist: rsclib
Requires-Dist: pgapy
Dynamic: author
Dynamic: home-page
Dynamic: license-file
Dynamic: platform
Dynamic: requires-python
